Staj_Projesi/Spi_Mode_3.vhd
----------------------------------------------------------------------------------
-- Company: 
-- Engineer: 
-- 
-- Create Date: 07/14/2026 11:37:36 AM
-- Design Name: 
-- Module Name: Spi_Mode_3 - Behavioral
-- Project Name: 
-- Target Devices: 
-- Tool Versions: 
-- Description: 
-- 
-- Dependencies: 
-- 
-- Revision:
-- Revision 0.01 - File Created
-- Additional Comments:
-- 
----------------------------------------------------------------------------------


library IEEE;
use IEEE.STD_LOGIC_1164.ALL;
use ieee.math_real.all;
use IEEE.numeric_std.all;

entity Spi_Mode_3 is
    generic(
        CLK_FREQ:integer := 50_000_000  ;
        SPI_FREQ:integer := 5_000_000   ;
        DATA_WIDTH:integer := 8         
    );
    Port ( clk_i : in STD_LOGIC;
           rst_i : in STD_LOGIC;
           start_trasfer_i: in STD_LOGIC;
           mosi_o : out STD_LOGIC;
           miso_i : in STD_LOGIC;
           sclk_o : out STD_LOGIC;
           cs_o : out STD_LOGIC;
           data_valid : out STD_LOGIC;
           rx_data : out STD_LOGIC_VECTOR (7 downto 0);
           data_buffer_i : in STD_LOGIC_VECTOR (7 downto 0));
end Spi_Mode_3;

architecture Behavioral of Spi_Mode_3 is
    constant BIT_LIMIT         : integer := CLK_FREQ / (SPI_FREQ * 2); 
    constant BIT_COUNTER_WIDTH : integer := integer(ceil(log2(real(BIT_LIMIT))));
    constant BIT_IDX_WIDTH     : integer := integer(ceil(log2(real(DATA_WIDTH))));
    
    signal bitcounter  : unsigned(BIT_COUNTER_WIDTH - 1 downto 0) := (others => '0');
    signal bit_idx     : unsigned(BIT_IDX_WIDTH downto 0)         := (others => '0'); 
    signal data_buffer : std_logic_vector(DATA_WIDTH - 1 downto 0) := (others => '0');
    
    type state_t is (IDLE, SHIFT, SAMPLE, DONE);
    signal state : state_t := IDLE;
begin

    process(clk_i)begin
        if rst_i = '0' then
            bit_idx     <= to_unsigned(7, bit_idx'length);  
            data_buffer <= (others => '0' );
            bitcounter  <= (others => '0' );
            state       <= IDLE                     ;
            data_valid  <= '0'                      ;
            sclk_o      <= '1'; 
            cs_o        <= '1'; 
            mosi_o      <= '0';
        elsif rising_edge(clk_i)then
            
            data_valid <= '0'; 
            
            case state is
                when IDLE =>
                    bit_idx     <= to_unsigned(7, bit_idx'length);
                    bitcounter  <= (others => '0' ) ;
                    sclk_o      <= '1'              ; 
                    cs_o        <= '1'              ;
                    
                    if(start_trasfer_i = '1') then 
                        cs_o        <= '0'          ;
                        data_buffer <= data_buffer_i;
                        state       <= SHIFT        ;
                    end if;
                    
                when SHIFT =>
                    if(bitcounter < BIT_LIMIT - 1 )then
                        bitcounter <= bitcounter + 1;
                    else
                        bitcounter  <= (others => '0' ) ;
                        state       <= SAMPLE           ;
                        sclk_o      <= '0'              ; 
                        mosi_o      <= data_buffer(to_integer(bit_idx));
                    end if;
                    
                when SAMPLE =>
                    if(bitcounter < BIT_LIMIT - 1 )then
                        bitcounter <= bitcounter + 1;
                    else
                        sclk_o      <= '1'              ; 
                        bitcounter  <= (others => '0' ) ;
                        data_buffer(to_integer(bit_idx)) <= miso_i;
                        
                        if (bit_idx = 0) then
                            state <= DONE;
                        else
                            bit_idx <= bit_idx - 1 ;
                            state <= SHIFT;
                        end if;
                    end if;
                    
                when DONE =>
                    if(bitcounter < BIT_LIMIT - 1 )then
                        bitcounter <= bitcounter + 1;
                    else 
                        sclk_o          <= '1'          ;
                        cs_o            <= '1'          ; 
                        data_valid      <= '1'          ; 
                        rx_data         <= data_buffer  ;
                        state           <= IDLE         ;
                    end if;
                    
                when others =>
                    state <= IDLE;
            end case;
        end if;
    end process;
end Behavioral;

pwm/pwm.srcs/sim_1/new/tb_spi.sv
`timescale 1ns / 1ps

module tb_spi();

    // ============================================================
    // Signals (SystemVerilog logic)
    // ============================================================
    logic clk_i;
    logic rst_i;
    logic start_trasfer_i;
    logic [7:0] data_buffer_i;
    logic miso_i;
    
    logic sclk_o;
    logic cs_o;
    logic data_valid;
    logic [7:0] rx_data;
    logic mosi_o;
    
    // Test variables
    int test_num = 0;
    int pass_count = 0;
    int fail_count = 0;
    
    // ============================================================
    // DUT Instantiation
    // ============================================================
    Spi_Mode_3 #(
        .CLK_FREQ(50_000_000),
        .SPI_FREQ(5_000_000),
        .DATA_WIDTH(8)
    )
    uut (
        .clk_i(clk_i),
        .rst_i(rst_i),
        .start_trasfer_i(start_trasfer_i),
        .mosi_o(mosi_o),
        .miso_i(miso_i),
        .sclk_o(sclk_o),
        .cs_o(cs_o),
        .data_valid(data_valid),
        .rx_data(rx_data),
        .data_buffer_i(data_buffer_i)
    );
    
    // ============================================================
    // Clock Generation (50 MHz)
    // ============================================================
    initial begin
        clk_i = 0;
        forever #10 clk_i = ~clk_i;
    end
    
    // ============================================================
    // MISO Slave Simulator
    // ============================================================
    logic [7:0] slave_tx_data;
    logic [3:0] bit_count;
    logic sclk_r1, sclk_r2;
    logic sclk_posedge;
    
    // Edge detection for SCLK
    always @(posedge clk_i) begin
        sclk_r1 <= sclk_o;
        sclk_r2 <= sclk_r1;
    end
    
    assign sclk_posedge = sclk_r2 & ~sclk_r1;
    
    // Slave: Send data MSB first on rising edge of SCLK
    always @(posedge sclk_posedge or posedge cs_o) begin
        if (cs_o) begin
            bit_count <= 0;
            miso_i <= 0;
        end else begin
            if (bit_count < 8) begin
                miso_i <= slave_tx_data[7 - bit_count];
                bit_count <= bit_count + 1;
            end
        end
    end
    
    // ============================================================
    // Verification Tasks
    // ============================================================
    
    task automatic test_init();
        $display("\n========================================");
        $display("    SPI Mode 3 Testbench (SystemVerilog)");
        $display("========================================");
        $display("CLK Frequency:  50 MHz");
        $display("SPI Frequency:  5 MHz");
        $display("Data Width:     8 bits");
        $display("Mode:           3 (CPOL=1, CPHA=1)");
        $display("========================================\n");
    endtask
    
    task automatic reset_dut();
        $display("[%0t] Asserting reset...", $time);
        rst_i = 0;
        data_buffer_i = 8'h00;
        start_trasfer_i = 0;
        miso_i = 0;
        slave_tx_data = 8'h00;
        bit_count = 0;
        
        #200;  // Hold reset
        rst_i = 1;
        #200;  // Wait after reset
        $display("[%0t] Reset complete\n", $time);
    endtask
    
    task automatic send_spi_byte(
        input logic [7:0] tx_data,
        input logic [7:0] expected_rx,
        input int test_id
    );
        test_num = test_id;
        $display("--- Test %0d ---", test_num);
        $display("[%0t] Sending: 0x%h, Expecting RX: 0x%h", $time, tx_data, expected_rx);
        
        slave_tx_data = expected_rx;
        data_buffer_i = tx_data;
        start_trasfer_i = 1;
        #20;
        start_trasfer_i = 0;
        
        // Wait for transfer to complete
        wait(data_valid);
        #50;
        
        // Verify results
        if (rx_data == expected_rx) begin
            $display("[%0t] ✓ PASS: RX Data = 0x%h (correct)", $time, rx_data);
            pass_count++;
        end else begin
            $display("[%0t] ✗ FAIL: RX Data = 0x%h (expected 0x%h)", $time, rx_data, expected_rx);
            fail_count++;
        end
        
        $display("[%0t] MOSI sent: 0x%h", $time, tx_data);
        
        #500;  // Inter-transfer delay
        $display("");
    endtask
    
    task automatic final_report();
        $display("\n========================================");
        $display("           FINAL TEST REPORT");
        $display("========================================");
        $display("Total Tests:  %0d", test_num);
        $display("Passed:       %0d", pass_count);
        $display("Failed:       %0d", fail_count);
        if (fail_count == 0) begin
            $display("Status:       ✓ ALL TESTS PASSED");
        end else begin
            $display("Status:       ✗ SOME TESTS FAILED");
        end
        $display("========================================\n");
    endtask
    
    // ============================================================
    // Main Test Sequence
    // ============================================================
    initial begin
        test_init();
        reset_dut();
        
        // Test 1: Send 0xBB, expect 0xAA from slave
        send_spi_byte(8'hBB, 8'hAA, 1);
        
        // Test 2: Send 0x55, expect 0x33
        send_spi_byte(8'h55, 8'h33, 2);
        
        // Test 3: Send 0xFF, expect 0xFF
        send_spi_byte(8'hFF, 8'hFF, 3);
        
        // Test 4: Send 0x00, expect 0x00
        send_spi_byte(8'h00, 8'h00, 4);
        
        // Test 5: Send 0xAA, expect 0x55
        send_spi_byte(8'hAA, 8'h55, 5);
        
        // Finish
        final_report();
        #1000;
        $finish;
    end
    
    // ============================================================
    // Waveform Dumping
    // ============================================================
    initial begin
        $dumpfile("tb_spi.vcd");
        $dumpvars(0, tb_spi);
    end
    
endmodule

pwm/pwm.sim/sim_1/behav/xsim/tb_spi.vcd
$date
   Tue Jul 14 13:25:22 2026
$end

$version
  2026.1
  $dumpfile ("tb_spi.vcd") 
$end

$timescale
  1ps
$end

$scope module tb_spi $end
$var reg 1 ! clk_i $end
$var reg 1 " rst_i $end
$var reg 1 # start_trasfer_i $end
$var reg 8 $ data_buffer_i [7:0] $end
$var reg 1 % miso_i $end
$var reg 1 & sclk_o $end
$var reg 1 ' cs_o $end
$var reg 1 ( data_valid $end
$var reg 8 ) rx_data [7:0] $end
$var reg 1 * mosi_o $end
$var reg 32 + test_num [31:0] $end
$var reg 32 , pass_count [31:0] $end
$var reg 32 - fail_count [31:0] $end
$var reg 8 . slave_tx_data [7:0] $end
$var reg 4 / bit_count [3:0] $end
$var reg 1 0 sclk_r1 $end
$var reg 1 1 sclk_r2 $end
$var reg 1 2 sclk_posedge $end
$scope module uut $end
$var wire 1 3 clk_i $end
$var wire 1 4 rst_i $end
$var wire 1 5 start_trasfer_i $end
$var wire 1 6 mosi_o $end
$var wire 1 7 miso_i $end
$var wire 1 8 sclk_o $end
$var wire 1 9 cs_o $end
$var wire 1 : data_valid $end
$var wire 8 ; rx_data $end
$var wire 8 < data_buffer_i $end
$var wire 3 = bitcounter $end
$var wire 4 > bit_idx $end
$var wire 8 ? data_buffer $end
$upscope $end
$scope task test_init $end
$upscope $end
$scope task reset_dut $end
$upscope $end
$scope task send_spi_byte $end
$upscope $end
$scope task final_report $end
$upscope $end
$upscope $end
$enddefinitions $end

#0
$dumpvars
0!
0"
0#
b0 $
0%
1&
1'
0(
bx )
0*
b0 +
b0 ,
b0 -
b0 .
b0 /
x0
x1
x2
03
04
05
06
07
18
19
0:
bx ;
b0 <
b0 =
b111 >
b0 ?
$end

#10000
1!
10
02
13
b0 ?

#20000
0!
03
b0 ?

#30000
1!
11
13
b0 ?

#40000
0!
03
b0 ?

#50000
1!
13
b0 ?

#60000
0!
03
b0 ?

#70000
1!
13
b0 ?

#80000
0!
03
b0 ?

#90000
1!
13
b0 ?

#100000
0!
03
b0 ?

#110000
1!
13
b0 ?

#120000
0!
03
b0 ?

#130000
1!
13
b0 ?

#140000
0!
03
b0 ?

#150000
1!
13
b0 ?

#160000
0!
03
b0 ?

#170000
1!
13
b0 ?

#180000
0!
03
b0 ?

#190000
1!
13
b0 ?

#200000
0!
1"
03
14

#210000
1!
13

#220000
0!
03

#230000
1!
13

#240000
0!
03

#250000
1!
13

#260000
0!
03

#270000
1!
13

#280000
0!
03

#290000
1!
13

#300000
0!
03

#310000
1!
13

#320000
0!
03

#330000
1!
13

#340000
0!
03

#350000
1!
13

#360000
0!
03

#370000
1!
13

#380000
0!
03

#390000
1!
13

#400000
0!
1#
b10111011 $
b1 +
b10101010 .
03
15
b10111011 <

#410000
1!
0'
13
09
b10111011 ?

#420000
0!
0#
03
05

#430000
1!
13
b1 =

#440000
0!
03

#450000
1!
13
b10 =

#460000
0!
03

#470000
1!
13
b11 =

#480000
0!
03

#490000
1!
13
b100 =

#500000
0!
03

#510000
1!
0&
1*
13
16
08
b0 =

#520000
0!
03

#530000
1!
1%
b1 /
00
12
13
17
b1 =

#540000
0!
03

#550000
1!
01
02
13
b10 =

#560000
0!
03

#570000
1!
13
b11 =

#580000
0!
03

#590000
1!
13
b100 =

#600000
0!
03

#610000
1!
1&
13
18
b0 =
b110 >
b10111011 ?

#620000
0!
03

#630000
1!
10
13
b1 =

#640000
0!
03

#650000
1!
11
13
b10 =

#660000
0!
03

#670000
1!
13
b11 =

#680000
0!
03

#690000
1!
13
b100 =

#700000
0!
03

#710000
1!
0&
0*
13
06
08
b0 =

#720000
0!
03

#730000
1!
0%
b10 /
00
12
13
07
b1 =

#740000
0!
03

#750000
1!
01
02
13
b10 =

#760000
0!
03

#770000
1!
13
b11 =

#780000
0!
03

#790000
1!
13
b100 =

#800000
0!
03

#810000
1!
1&
13
18
b0 =
b101 >
b10111011 ?

#820000
0!
03

#830000
1!
10
13
b1 =

#840000
0!
03

#850000
1!
11
13
b10 =

#860000
0!
03

#870000
1!
13
b11 =

#880000
0!
03

#890000
1!
13
b100 =

#900000
0!
03

#910000
1!
0&
1*
13
16
08
b0 =

#920000
0!
03

#930000
1!
1%
b11 /
00
12
13
17
b1 =

#940000
0!
03

#950000
1!
01
02
13
b10 =

#960000
0!
03

#970000
1!
13
b11 =

#980000
0!
03

#990000
1!
13
b100 =

#1000000
0!
03

#1010000
1!
1&
13
18
b0 =
b100 >
b10111011 ?

#1020000
0!
03

#1030000
1!
10
13
b1 =

#1040000
0!
03

#1050000
1!
11
13
b10 =

#1060000
0!
03

#1070000
1!
13
b11 =

#1080000
0!
03

#1090000
1!
13
b100 =

#1100000
0!
03

#1110000
1!
0&
13
08
b0 =

#1120000
0!
03

#1130000
1!
0%
b100 /
00
12
13
07
b1 =

#1140000
0!
03

#1150000
1!
01
02
13
b10 =

#1160000
0!
03

#1170000
1!
13
b11 =

#1180000
0!
03

#1190000
1!
13
b100 =

#1200000
0!
03

#1210000
1!
1&
13
18
b0 =
b11 >
b10101011 ?

#1220000
0!
03

#1230000
1!
10
13
b1 =

#1240000
0!
03

#1250000
1!
11
13
b10 =

#1260000
0!
03

#1270000
1!
13
b11 =

#1280000
0!
03

#1290000
1!
13
b100 =

#1300000
0!
03

#1310000
1!
0&
13
08
b0 =

#1320000
0!
03

#1330000
1!
1%
b101 /
00
12
13
17
b1 =

#1340000
0!
03

#1350000
1!
01
02
13
b10 =

#1360000
0!
03

#1370000
1!
13
b11 =

#1380000
0!
03

#1390000
1!
13
b100 =

#1400000
0!
03

#1410000
1!
1&
13
18
b0 =
b10 >
b10101011 ?

#1420000
0!
03

#1430000
1!
10
13
b1 =

#1440000
0!
03

#1450000
1!
11
13
b10 =

#1460000
0!
03

#1470000
1!
13
b11 =

#1480000
0!
03

#1490000
1!
13
b100 =

#1500000
0!
03

#1510000
1!
0&
0*
13
06
08
b0 =

#1520000
0!
03

#1530000
1!
0%
b110 /
00
12
13
07
b1 =

#1540000
0!
03

#1550000
1!
01
02
13
b10 =

#1560000
0!
03

#1570000
1!
13
b11 =

#1580000
0!
03

#1590000
1!
13
b100 =

#1600000
0!
03

#1610000
1!
1&
13
18
b0 =
b1 >
b10101011 ?

#1620000
0!
03

#1630000
1!
10
13
b1 =

#1640000
0!
03

#1650000
1!
11
13
b10 =

#1660000
0!
03

#1670000
1!
13
b11 =

#1680000
0!
03

#1690000
1!
13
b100 =

#1700000
0!
03

#1710000
1!
0&
1*
13
16
08
b0 =

#1720000
0!
03

#1730000
1!
1%
b111 /
00
12
13
17
b1 =

#1740000
0!
03

#1750000
1!
01
02
13
b10 =

#1760000
0!
03

#1770000
1!
13
b11 =

#1780000
0!
03

#1790000
1!
13
b100 =

#1800000
0!
03

#1810000
1!
1&
13
18
b0 =
b0 >
b10101011 ?

#1820000
0!
03

#1830000
1!
10
13
b1 =

#1840000
0!
03

#1850000
1!
11
13
b10 =

#1860000
0!
03

#1870000
1!
13
b11 =

#1880000
0!
03

#1890000
1!
13
b100 =

#1900000
0!
03

#1910000
1!
0&
13
08
b0 =

#1920000
0!
03

#1930000
1!
0%
b1000 /
00
12
13
07
b1 =

#1940000
0!
03

#1950000
1!
01
02
13
b10 =

#1960000
0!
03

#1970000
1!
13
b11 =

#1980000
0!
03

#1990000
1!
13
b100 =

#2000000
0!
03

#2010000
1!
1&
13
18
b0 =
b10101010 ?

#2020000
0!
03

#2030000
1!
10
13
b1 =

#2040000
0!
03

#2050000
1!
11
13
b10 =

#2060000
0!
03

#2070000
1!
13
b11 =

#2080000
0!
03

#2090000
1!
13
b100 =

#2100000
0!
03

#2110000
1!
1'
1(
b10101010 )
b0 /
13
19
1:
b10101010 ;

#2120000
0!
03

#2130000
1!
0(
13
0:
b0 =
b111 >

#2140000
0!
03

#2150000
1!
13

#2160000
0!
b1 ,
03

